mbti/__init__.py
mbti/calculator.py
mbti/entry_point.py
mbti/questions.py
mbti/results.py
mbti/test.py
mbti/data/question_registry.json
mbti/data/questions_28.json
mbti/data/questions_40.json
mbti/data/questions_93.json
mbti/i18n/__init__.py
mbti/i18n/core.py
mbti/i18n/en.json
mbti/i18n/zh.json
mbti_test-0.3.2.dist-info/LICENSE
mbti_test-0.3.2.dist-info/METADATA
mbti_test-0.3.2.dist-info/WHEEL
mbti_test-0.3.2.dist-info/entry_points.txt
mbti_test-0.3.2.dist-info/top_level.txt
mbti_test-0.3.2.dist-info/RECORD
