Metadata-Version: 2.1
Name: mbti-test
Version: 0.3.2
Summary: A command line application for taking the MBTI personality test
Home-page: https://github.com/luhuadong/mbti-test
Author: luhuadong
Author-email: luhuadong@163.com
Classifier: Programming Language :: Python :: 3
Classifier: License :: OSI Approved :: MIT License
Classifier: Operating System :: OS Independent
Requires-Python: >=3.6
License-File: LICENSE
